setup.py
vtr_storages/__init__.py
vtr_storages/locks.py
vtr_storages/move.py
vtr_storages.egg-info/PKG-INFO
vtr_storages.egg-info/SOURCES.txt
vtr_storages.egg-info/dependency_links.txt
vtr_storages.egg-info/requires.txt
vtr_storages.egg-info/top_level.txt
vtr_storages/storages/__init__.py
vtr_storages/storages/test.py
vtr_storages/storages/filesystem/__init__.py
vtr_storages/storages/filesystem/test.py
vtr_storages/storages/kvdb/__init__.py
vtr_storages/storages/kvdb/test.py