Metadata-Version: 1.1
Name: vtr-storages
Version: 0.1.1
Summary: Storage collection, filesystem forked from django
Home-page: https://github.com/viatoriche/vtr_storages
Author: viatoriche
Author-email: maxim@via-net.org
License: MIT
Download-URL: https://github.com/viatoriche/vtr_storages/tarball/0.1.1
Platform: UNKNOWN
